gitaflow-0.1.dist-info/top_level.txt
gitaflow-0.1.dist-info/RECORD
gitaflow-0.1.dist-info/WHEEL
gitaflow-0.1.dist-info/METADATA
gitaflow-0.1.dist-info/DESCRIPTION.rst
gitaflow-0.1.dist-info/metadata.json
gitaflow-0.1.dist-info/entry_points.txt
gitaflow/__init__.py
gitaflow/revert.py
gitaflow/debug.py
gitaflow/args.py
gitaflow/merge.py
gitaflow/checkout.py
gitaflow/common.py
gitaflow/start.py
gitaflow/rebase.py
gitaflow/init.py
gitaflow/topic.py
gitaflow/finish.py
gitaflow/continue_.py
gitaflow/constants.py
gitaflow/execute.py
gitaflow/iteration.py
gitaflow/list_.py
